{"data": "{\"randomise_slider_handle\": true, \"show_number_on_slider\": false, \"randomise_pages\": true, \"labels\": [\"Strong interference\", \"No interference\"], \"site_url\": \"http://localhost:4000\", \"continuous_playback\": true, \"randomise_sounds_within_page\": true, \"allow_slider_sort\": true, \"back_button_can_exit_test\": false, \"pages\": [{\"is_replicate\": false, \"order\": 8, \"name\": \"vocals-47-SAR\", \"sounds\": [{\"url\": \"sounds/vocals-47-SAR/Quality.wav\", \"rating\": 100, \"name\": \"Quality\"}, {\"url\": \"sounds/vocals-47-SAR/STO1.wav\", \"rating\": 69, \"name\": \"STO1\"}, {\"url\": \"sounds/vocals-47-SAR/KAM1.wav\", \"rating\": 91, \"name\": \"KAM1\"}, {\"url\": \"sounds/vocals-47-SAR/Interferer.wav\", \"rating\": 0, \"name\": \"Interferer\"}, {\"url\": \"sounds/vocals-47-SAR/OZE.wav\", \"rating\": 8, \"name\": \"OZE\"}, {\"url\": \"sounds/vocals-47-SAR/ref.wav\", \"rating\": 100, \"name\": \"ref\"}, {\"url\": \"sounds/vocals-47-SAR/RAF1.wav\", \"rating\": 20, \"name\": \"RAF1\"}, {\"url\": \"sounds/vocals-47-SAR/GRA3.wav\", \"rating\": 26, \"name\": \"GRA3\"}], \"duration\": 70.69315192743761, \"reference_url\": \"sounds/vocals-47-SAR/ref.wav\"}, {\"is_replicate\": false, \"order\": 7, \"name\": \"vocals-18-SIR\", \"sounds\": [{\"url\": \"sounds/vocals-18-SIR/HUA.wav\", \"rating\": 7, \"name\": \"HUA\"}, {\"url\": \"sounds/vocals-18-SIR/Quality.wav\", \"rating\": 97, \"name\": \"Quality\"}, {\"url\": \"sounds/vocals-18-SIR/Interferer.wav\", \"rating\": 0, \"name\": \"Interferer\"}, {\"url\": \"sounds/vocals-18-SIR/UHL1.wav\", \"rating\": 58, \"name\": \"UHL1\"}, {\"url\": \"sounds/vocals-18-SIR/OZE.wav\", \"rating\": 10, \"name\": \"OZE\"}, {\"url\": \"sounds/vocals-18-SIR/ref.wav\", \"rating\": 100, \"name\": \"ref\"}, {\"url\": \"sounds/vocals-18-SIR/NUG1.wav\", \"rating\": 100, \"name\": \"NUG1\"}, {\"url\": \"sounds/vocals-18-SIR/GRA3.wav\", \"rating\": 46, \"name\": \"GRA3\"}], \"duration\": 67.50040816326532, \"reference_url\": \"sounds/vocals-18-SIR/ref.wav\"}, {\"is_replicate\": false, \"order\": 11, \"name\": \"vocals-20-SAR\", \"sounds\": [{\"url\": \"sounds/vocals-20-SAR/KAM2.wav\", \"rating\": 31, \"name\": \"KAM2\"}, {\"url\": \"sounds/vocals-20-SAR/HUA.wav\", \"rating\": 10, \"name\": \"HUA\"}, {\"url\": \"sounds/vocals-20-SAR/Quality.wav\", \"rating\": 96, \"name\": \"Quality\"}, {\"url\": \"sounds/vocals-20-SAR/Interferer.wav\", \"rating\": 0, \"name\": \"Interferer\"}, {\"url\": \"sounds/vocals-20-SAR/DUR.wav\", \"rating\": 50, \"name\": \"DUR\"}, {\"url\": \"sounds/vocals-20-SAR/ref.wav\", \"rating\": 100, \"name\": \"ref\"}, {\"url\": \"sounds/vocals-20-SAR/CHA.wav\", \"rating\": 21, \"name\": \"CHA\"}, {\"url\": \"sounds/vocals-20-SAR/KON.wav\", \"rating\": 38, \"name\": \"KON\"}], \"duration\": 66.73414965986399, \"reference_url\": \"sounds/vocals-20-SAR/ref.wav\"}, {\"is_replicate\": true, \"order\": 6, \"name\": \"vocals-26-SIR\", \"sounds\": [{\"url\": \"sounds/vocals-26-SIR/HUA.wav\", \"rating\": 8, \"name\": \"HUA\"}, {\"url\": \"sounds/vocals-26-SIR/Quality.wav\", \"rating\": 94, \"name\": \"Quality\"}, {\"url\": \"sounds/vocals-26-SIR/KAM1.wav\", \"rating\": 43, \"name\": \"KAM1\"}, {\"url\": \"sounds/vocals-26-SIR/Interferer.wav\", \"rating\": 0, \"name\": \"Interferer\"}, {\"url\": \"sounds/vocals-26-SIR/ref.wav\", \"rating\": 100, \"name\": \"ref\"}, {\"url\": \"sounds/vocals-26-SIR/RAF1.wav\", \"rating\": 24, \"name\": \"RAF1\"}, {\"url\": \"sounds/vocals-26-SIR/JEO1.wav\", \"rating\": 62, \"name\": \"JEO1\"}, {\"url\": \"sounds/vocals-26-SIR/KON.wav\", \"rating\": 50, \"name\": \"KON\"}], \"duration\": 93.29777777777781, \"reference_url\": \"sounds/vocals-26-SIR/ref.wav\"}, {\"is_replicate\": false, \"order\": 13, \"name\": \"vocals-49-SIR\", \"sounds\": [{\"url\": \"sounds/vocals-49-SIR/HUA.wav\", \"rating\": 6, \"name\": \"HUA\"}, {\"url\": \"sounds/vocals-49-SIR/Quality.wav\", \"rating\": 98, \"name\": \"Quality\"}, {\"url\": \"sounds/vocals-49-SIR/NUG2.wav\", \"rating\": 91, \"name\": \"NUG2\"}, {\"url\": \"sounds/vocals-49-SIR/JEO2.wav\", \"rating\": 35, \"name\": \"JEO2\"}, {\"url\": \"sounds/vocals-49-SIR/KAM1.wav\", \"rating\": 83, \"name\": \"KAM1\"}, {\"url\": \"sounds/vocals-49-SIR/Interferer.wav\", \"rating\": 0, \"name\": \"Interferer\"}, {\"url\": \"sounds/vocals-49-SIR/ref.wav\", \"rating\": 99, \"name\": \"ref\"}, {\"url\": \"sounds/vocals-49-SIR/STO2.wav\", \"rating\": 47, \"name\": \"STO2\"}], \"duration\": 91.39374149659852, \"reference_url\": \"sounds/vocals-49-SIR/ref.wav\"}, {\"is_replicate\": false, \"order\": 16, \"name\": \"vocals-41-SIR\", \"sounds\": [{\"url\": \"sounds/vocals-41-SIR/HUA.wav\", \"rating\": 3, \"name\": \"HUA\"}, {\"url\": \"sounds/vocals-41-SIR/Quality.wav\", \"rating\": 89, \"name\": \"Quality\"}, {\"url\": \"sounds/vocals-41-SIR/RAF3.wav\", \"rating\": 8, \"name\": \"RAF3\"}, {\"url\": \"sounds/vocals-41-SIR/Interferer.wav\", \"rating\": 0, \"name\": \"Interferer\"}, {\"url\": \"sounds/vocals-41-SIR/DUR.wav\", \"rating\": 46, \"name\": \"DUR\"}, {\"url\": \"sounds/vocals-41-SIR/UHL1.wav\", \"rating\": 63, \"name\": \"UHL1\"}, {\"url\": \"sounds/vocals-41-SIR/ref.wav\", \"rating\": 99, \"name\": \"ref\"}, {\"url\": \"sounds/vocals-41-SIR/NUG1.wav\", \"rating\": 57, \"name\": \"NUG1\"}], \"duration\": 66.67609977324264, \"reference_url\": \"sounds/vocals-41-SIR/ref.wav\"}, {\"is_replicate\": false, \"order\": 3, \"name\": \"vocals-25-SAR\", \"sounds\": [{\"url\": \"sounds/vocals-25-SAR/HUA.wav\", \"rating\": 5, \"name\": \"HUA\"}, {\"url\": \"sounds/vocals-25-SAR/Quality.wav\", \"rating\": 99, \"name\": \"Quality\"}, {\"url\": \"sounds/vocals-25-SAR/RAF3.wav\", \"rating\": 22, \"name\": \"RAF3\"}, {\"url\": \"sounds/vocals-25-SAR/Interferer.wav\", \"rating\": 0, \"name\": \"Interferer\"}, {\"url\": \"sounds/vocals-25-SAR/ref.wav\", \"rating\": 100, \"name\": \"ref\"}, {\"url\": \"sounds/vocals-25-SAR/GRA2.wav\", \"rating\": 98, \"name\": \"GRA2\"}, {\"url\": \"sounds/vocals-25-SAR/RAF1.wav\", \"rating\": 19, \"name\": \"RAF1\"}, {\"url\": \"sounds/vocals-25-SAR/KON.wav\", \"rating\": 79, \"name\": \"KON\"}], \"duration\": 135.88317460317467, \"reference_url\": \"sounds/vocals-25-SAR/ref.wav\"}, {\"is_replicate\": false, \"order\": 4, \"name\": \"vocals-12-SAR\", \"sounds\": [{\"url\": \"sounds/vocals-12-SAR/KAM2.wav\", \"rating\": 59, \"name\": \"KAM2\"}, {\"url\": \"sounds/vocals-12-SAR/Quality.wav\", \"rating\": 93, \"name\": \"Quality\"}, {\"url\": \"sounds/vocals-12-SAR/Interferer.wav\", \"rating\": 0, \"name\": \"Interferer\"}, {\"url\": \"sounds/vocals-12-SAR/DUR.wav\", \"rating\": 30, \"name\": \"DUR\"}, {\"url\": \"sounds/vocals-12-SAR/ref.wav\", \"rating\": 100, \"name\": \"ref\"}, {\"url\": \"sounds/vocals-12-SAR/GRA2.wav\", \"rating\": 91, \"name\": \"GRA2\"}, {\"url\": \"sounds/vocals-12-SAR/KON.wav\", \"rating\": 28, \"name\": \"KON\"}, {\"url\": \"sounds/vocals-12-SAR/GRA3.wav\", \"rating\": 24, \"name\": \"GRA3\"}], \"duration\": 94.45877551020408, \"reference_url\": \"sounds/vocals-12-SAR/ref.wav\"}, {\"is_replicate\": false, \"order\": 9, \"name\": \"vocals-19-SIR\", \"sounds\": [{\"url\": \"sounds/vocals-19-SIR/KAM2.wav\", \"rating\": 33, \"name\": \"KAM2\"}, {\"url\": \"sounds/vocals-19-SIR/HUA.wav\", \"rating\": 4, \"name\": \"HUA\"}, {\"url\": \"sounds/vocals-19-SIR/Quality.wav\", \"rating\": 100, \"name\": \"Quality\"}, {\"url\": \"sounds/vocals-19-SIR/KAM1.wav\", \"rating\": 94, \"name\": \"KAM1\"}, {\"url\": \"sounds/vocals-19-SIR/Interferer.wav\", \"rating\": 0, \"name\": \"Interferer\"}, {\"url\": \"sounds/vocals-19-SIR/ref.wav\", \"rating\": 100, \"name\": \"ref\"}, {\"url\": \"sounds/vocals-19-SIR/KON.wav\", \"rating\": 50, \"name\": \"KON\"}, {\"url\": \"sounds/vocals-19-SIR/GRA3.wav\", \"rating\": 27, \"name\": \"GRA3\"}], \"duration\": 52.593197278911475, \"reference_url\": \"sounds/vocals-19-SIR/ref.wav\"}, {\"is_replicate\": false, \"order\": 10, \"name\": \"vocals-42-SAR\", \"sounds\": [{\"url\": \"sounds/vocals-42-SAR/KAM2.wav\", \"rating\": 52, \"name\": \"KAM2\"}, {\"url\": \"sounds/vocals-42-SAR/Quality.wav\", \"rating\": 95, \"name\": \"Quality\"}, {\"url\": \"sounds/vocals-42-SAR/UHL3.wav\", \"rating\": 60, \"name\": \"UHL3\"}, {\"url\": \"sounds/vocals-42-SAR/Interferer.wav\", \"rating\": 1, \"name\": \"Interferer\"}, {\"url\": \"sounds/vocals-42-SAR/ref.wav\", \"rating\": 100, \"name\": \"ref\"}, {\"url\": \"sounds/vocals-42-SAR/CHA.wav\", \"rating\": 24, \"name\": \"CHA\"}, {\"url\": \"sounds/vocals-42-SAR/NUG3.wav\", \"rating\": 100, \"name\": \"NUG3\"}, {\"url\": \"sounds/vocals-42-SAR/KON.wav\", \"rating\": 7, \"name\": \"KON\"}], \"duration\": 74.39673469387753, \"reference_url\": \"sounds/vocals-42-SAR/ref.wav\"}, {\"is_replicate\": false, \"order\": 2, \"name\": \"vocals-24-SAR\", \"sounds\": [{\"url\": \"sounds/vocals-24-SAR/HUA.wav\", \"rating\": 6, \"name\": \"HUA\"}, {\"url\": \"sounds/vocals-24-SAR/Quality.wav\", \"rating\": 100, \"name\": \"Quality\"}, {\"url\": \"sounds/vocals-24-SAR/RAF2.wav\", \"rating\": 11, \"name\": \"RAF2\"}, {\"url\": \"sounds/vocals-24-SAR/KAM1.wav\", \"rating\": 54, \"name\": \"KAM1\"}, {\"url\": \"sounds/vocals-24-SAR/Interferer.wav\", \"rating\": 0, \"name\": \"Interferer\"}, {\"url\": \"sounds/vocals-24-SAR/ref.wav\", \"rating\": 100, \"name\": \"ref\"}, {\"url\": \"sounds/vocals-24-SAR/STO2.wav\", \"rating\": 49, \"name\": \"STO2\"}, {\"url\": \"sounds/vocals-24-SAR/GRA3.wav\", \"rating\": 15, \"name\": \"GRA3\"}], \"duration\": 96.20027210884359, \"reference_url\": \"sounds/vocals-24-SAR/ref.wav\"}, {\"is_replicate\": false, \"order\": 12, \"name\": \"vocals-48-SAR\", \"sounds\": [{\"url\": \"sounds/vocals-48-SAR/KAM2.wav\", \"rating\": 48, \"name\": \"KAM2\"}, {\"url\": \"sounds/vocals-48-SAR/HUA.wav\", \"rating\": 14, \"name\": \"HUA\"}, {\"url\": \"sounds/vocals-48-SAR/Quality.wav\", \"rating\": 100, \"name\": \"Quality\"}, {\"url\": \"sounds/vocals-48-SAR/RAF3.wav\", \"rating\": 10, \"name\": \"RAF3\"}, {\"url\": \"sounds/vocals-48-SAR/Interferer.wav\", \"rating\": 0, \"name\": \"Interferer\"}, {\"url\": \"sounds/vocals-48-SAR/ref.wav\", \"rating\": 100, \"name\": \"ref\"}, {\"url\": \"sounds/vocals-48-SAR/NUG3.wav\", \"rating\": 65, \"name\": \"NUG3\"}, {\"url\": \"sounds/vocals-48-SAR/JEO1.wav\", \"rating\": 30, \"name\": \"JEO1\"}], \"duration\": 68.31310657596373, \"reference_url\": \"sounds/vocals-48-SAR/ref.wav\"}, {\"is_replicate\": false, \"order\": 15, \"name\": \"vocals-30-SIR\", \"sounds\": [{\"url\": \"sounds/vocals-30-SIR/HUA.wav\", \"rating\": 5, \"name\": \"HUA\"}, {\"url\": \"sounds/vocals-30-SIR/Quality.wav\", \"rating\": 98, \"name\": \"Quality\"}, {\"url\": \"sounds/vocals-30-SIR/JEO2.wav\", \"rating\": 41, \"name\": \"JEO2\"}, {\"url\": \"sounds/vocals-30-SIR/Interferer.wav\", \"rating\": 0, \"name\": \"Interferer\"}, {\"url\": \"sounds/vocals-30-SIR/ref.wav\", \"rating\": 100, \"name\": \"ref\"}, {\"url\": \"sounds/vocals-30-SIR/CHA.wav\", \"rating\": 23, \"name\": \"CHA\"}, {\"url\": \"sounds/vocals-30-SIR/RAF1.wav\", \"rating\": 13, \"name\": \"RAF1\"}, {\"url\": \"sounds/vocals-30-SIR/NUG3.wav\", \"rating\": 83, \"name\": \"NUG3\"}], \"duration\": 53.638095238095275, \"reference_url\": \"sounds/vocals-30-SIR/ref.wav\"}, {\"is_replicate\": false, \"order\": 5, \"name\": \"vocals-45-SIR\", \"sounds\": [{\"url\": \"sounds/vocals-45-SIR/KAM2.wav\", \"rating\": 82, \"name\": \"KAM2\"}, {\"url\": \"sounds/vocals-45-SIR/HUA.wav\", \"rating\": 16, \"name\": \"HUA\"}, {\"url\": \"sounds/vocals-45-SIR/Quality.wav\", \"rating\": 95, \"name\": \"Quality\"}, {\"url\": \"sounds/vocals-45-SIR/STO1.wav\", \"rating\": 42, \"name\": \"STO1\"}, {\"url\": \"sounds/vocals-45-SIR/RAF2.wav\", \"rating\": 27, \"name\": \"RAF2\"}, {\"url\": \"sounds/vocals-45-SIR/Interferer.wav\", \"rating\": 0, \"name\": \"Interferer\"}, {\"url\": \"sounds/vocals-45-SIR/UHL1.wav\", \"rating\": 46, \"name\": \"UHL1\"}, {\"url\": \"sounds/vocals-45-SIR/ref.wav\", \"rating\": 100, \"name\": \"ref\"}], \"duration\": 103.07337868480715, \"reference_url\": \"sounds/vocals-45-SIR/ref.wav\"}, {\"is_replicate\": false, \"order\": 1, \"name\": \"vocals-10-SIR\", \"sounds\": [{\"url\": \"sounds/vocals-10-SIR/HUA.wav\", \"rating\": 26, \"name\": \"HUA\"}, {\"url\": \"sounds/vocals-10-SIR/Quality.wav\", \"rating\": 97, \"name\": \"Quality\"}, {\"url\": \"sounds/vocals-10-SIR/NUG2.wav\", \"rating\": 73, \"name\": \"NUG2\"}, {\"url\": \"sounds/vocals-10-SIR/RAF2.wav\", \"rating\": 30, \"name\": \"RAF2\"}, {\"url\": \"sounds/vocals-10-SIR/KAM1.wav\", \"rating\": 92, \"name\": \"KAM1\"}, {\"url\": \"sounds/vocals-10-SIR/Interferer.wav\", \"rating\": 0, \"name\": \"Interferer\"}, {\"url\": \"sounds/vocals-10-SIR/ref.wav\", \"rating\": 100, \"name\": \"ref\"}, {\"url\": \"sounds/vocals-10-SIR/KON.wav\", \"rating\": 9, \"name\": \"KON\"}], \"duration\": 90.73197278911562, \"reference_url\": \"sounds/vocals-10-SIR/ref.wav\"}, {\"is_replicate\": false, \"order\": 0, \"name\": \"vocals-11-SAR\", \"sounds\": [{\"url\": \"sounds/vocals-11-SAR/HUA.wav\", \"rating\": 4, \"name\": \"HUA\"}, {\"url\": \"sounds/vocals-11-SAR/Quality.wav\", \"rating\": 99, \"name\": \"Quality\"}, {\"url\": \"sounds/vocals-11-SAR/STO1.wav\", \"rating\": 63, \"name\": \"STO1\"}, {\"url\": \"sounds/vocals-11-SAR/RAF2.wav\", \"rating\": 27, \"name\": \"RAF2\"}, {\"url\": \"sounds/vocals-11-SAR/KAM1.wav\", \"rating\": 92, \"name\": \"KAM1\"}, {\"url\": \"sounds/vocals-11-SAR/Interferer.wav\", \"rating\": 0, \"name\": \"Interferer\"}, {\"url\": \"sounds/vocals-11-SAR/ref.wav\", \"rating\": 99, \"name\": \"ref\"}, {\"url\": \"sounds/vocals-11-SAR/GRA3.wav\", \"rating\": 32, \"name\": \"GRA3\"}], \"duration\": 87.71337868480731, \"reference_url\": \"sounds/vocals-11-SAR/ref.wav\"}, {\"is_replicate\": true, \"order\": 14, \"name\": \"vocals-26-SIR\", \"sounds\": [{\"url\": \"sounds/vocals-26-SIR/HUA.wav\", \"rating\": 8, \"name\": \"HUA\"}, {\"url\": \"sounds/vocals-26-SIR/Quality.wav\", \"rating\": 99, \"name\": \"Quality\"}, {\"url\": \"sounds/vocals-26-SIR/KAM1.wav\", \"rating\": 51, \"name\": \"KAM1\"}, {\"url\": \"sounds/vocals-26-SIR/Interferer.wav\", \"rating\": 0, \"name\": \"Interferer\"}, {\"url\": \"sounds/vocals-26-SIR/ref.wav\", \"rating\": 100, \"name\": \"ref\"}, {\"url\": \"sounds/vocals-26-SIR/RAF1.wav\", \"rating\": 21, \"name\": \"RAF1\"}, {\"url\": \"sounds/vocals-26-SIR/JEO1.wav\", \"rating\": 55, \"name\": \"JEO1\"}, {\"url\": \"sounds/vocals-26-SIR/KON.wav\", \"rating\": 45, \"name\": \"KON\"}], \"duration\": 107.57804988662133, \"reference_url\": \"sounds/vocals-26-SIR/ref.wav\"}], \"allow_submission\": true, \"add_consistency_check\": true, \"must_play_all_samples_to_continue\": true, \"next_url\": \"http://localhost:4000\", \"loop_playback\": true}", "date": "2017-09-29T11:29:04.960Z", "name": "K", "experiment_id": "interferer", "_id": "662aa910-a509-11e7-988c-0da33b08c6af"}